keyboarded/__init__.py
keyboarded/__main__.py
keyboarded/_canonical_names.py
keyboarded/_darwinkeyboard.py
keyboarded/_darwinmouse.py
keyboarded/_generic.py
keyboarded/_keyboard_event.py
keyboarded/_keyboard_tests.py
keyboarded/_mouse_event.py
keyboarded/_mouse_tests.py
keyboarded/_nixcommon.py
keyboarded/_nixkeyboard.py
keyboarded/_nixmouse.py
keyboarded/_winkeyboard.py
keyboarded/_winmouse.py
keyboarded/mouse.py
keyboarded-1.0.0.dist-info/LICENSE.txt
keyboarded-1.0.0.dist-info/METADATA
keyboarded-1.0.0.dist-info/WHEEL
keyboarded-1.0.0.dist-info/top_level.txt
keyboarded-1.0.0.dist-info/RECORD
