Metadata-Version: 2.1
Name: keyboarded
Version: 1.0.0
Summary: Hook and simulate keyboard events on Windows and Linux
Home-page: https://github.com/jecrs/keyboarded
Author: jecrs
Author-email: jecrsouza@gmail.com
License: CC-BY-SA-4.0
Keywords: keyboard hook simulate hotkey
Classifier: Development Status :: 4 - Beta
Classifier: License :: OSI Approved :: MIT License
Classifier: Operating System :: Microsoft :: Windows
Classifier: Operating System :: Unix
Classifier: Operating System :: MacOS :: MacOS X
Classifier: Programming Language :: Python :: 2
Classifier: Programming Language :: Python :: 3
Classifier: Topic :: Software Development :: Libraries :: Python Modules
Classifier: Topic :: Utilities
License-File: LICENSE.txt
Requires-Dist: pyobjc ; sys_platform == "darwin"
